{
    "fetch": [
        {
            "name": "fetch",
            "request": {
                "account_sid": "ACaaaaaaaaaaaaaaaaaaaaaaaaaaaaaaaa",
                "form_params": {},
                "method": "GET",
                "query_params": {},
                "url": "https://fax.twilio.com/v1/Faxes/FXaaaaaaaaaaaaaaaaaaaaaaaaaaaaaaaa/Media/MEaaaaaaaaaaaaaaaaaaaaaaaaaaaaaaaa"
            },
            "downstream_request": {
                "form_params": {},
                "method": "GET",
                "query_params": {},
                "url": "/v1/Faxes/FXaaaaaaaaaaaaaaaaaaaaaaaaaaaaaaaa/Media/MEaaaaaaaaaaaaaaaaaaaaaaaaaaaaaaaa"
            },
            "downstream_response": {
                "content": {
                    "sid": "MEaaaaaaaaaaaaaaaaaaaaaaaaaaaaaaaa",
                    "account_sid": "ACaaaaaaaaaaaaaaaaaaaaaaaaaaaaaaaa",
                    "fax_sid": "FXaaaaaaaaaaaaaaaaaaaaaaaaaaaaaaaa",
                    "content_type": "application/pdf",
                    "date_created": "2015-07-30T20:00:00Z",
                    "date_updated": "2015-07-30T20:00:00Z",
                    "uri": "/v1/Faxes/FXaaaaaaaaaaaaaaaaaaaaaaaaaaaaaaaa/Media/MEaaaaaaaaaaaaaaaaaaaaaaaaaaaaaaaa"
                },
                "status_code": 200
            },
            "response": {
                "content": {
                    "account_sid": "ACaaaaaaaaaaaaaaaaaaaaaaaaaaaaaaaa",
                    "content_type": "application/pdf",
                    "date_created": "2015-07-30T20:00:00Z",
                    "date_updated": "2015-07-30T20:00:00Z",
                    "fax_sid": "FXaaaaaaaaaaaaaaaaaaaaaaaaaaaaaaaa",
                    "sid": "MEaaaaaaaaaaaaaaaaaaaaaaaaaaaaaaaa",
                    "url": "https://fax.twilio.com/v1/Faxes/FXaaaaaaaaaaaaaaaaaaaaaaaaaaaaaaaa/Media/MEaaaaaaaaaaaaaaaaaaaaaaaaaaaaaaaa"
                },
                "status_code": 200
            }
        }
    ],
    "read": [
        {
            "name": "read",
            "request": {
                "account_sid": "ACaaaaaaaaaaaaaaaaaaaaaaaaaaaaaaaa",
                "form_params": {},
                "method": "GET",
                "query_params": {},
                "url": "https://fax.twilio.com/v1/Faxes/FXaaaaaaaaaaaaaaaaaaaaaaaaaaaaaaaa/Media"
            },
            "downstream_request": {
                "form_params": {},
                "method": "GET",
                "query_params": {},
                "url": "/v1/Faxes/FXaaaaaaaaaaaaaaaaaaaaaaaaaaaaaaaa/Media"
            },
            "downstream_response": {
                "content": {
                    "media": [{
                        "sid": "MEaaaaaaaaaaaaaaaaaaaaaaaaaaaaaaaa",
                        "account_sid": "ACaaaaaaaaaaaaaaaaaaaaaaaaaaaaaaaa",
                        "fax_sid": "FXaaaaaaaaaaaaaaaaaaaaaaaaaaaaaaaa",
                        "content_type": "application/pdf",
                        "date_created": "2015-07-30T20:00:00Z",
                        "date_updated": "2015-07-30T20:00:00Z",
                        "uri": "/v1/Faxes/FXaaaaaaaaaaaaaaaaaaaaaaaaaaaaaaaa/Media/MEaaaaaaaaaaaaaaaaaaaaaaaaaaaaaaaa"
                    }],
                    "meta": {
                        "direct_token": true,
                        "key": "media",
                        "next_token": null,
                        "page": 0,
                        "page_size": 0,
                        "page_token": null,
                        "previous_token": null
                    }
                },
                "status_code": 200
            },
            "response": {
                "content": {
                    "media": [{
                        "sid": "MEaaaaaaaaaaaaaaaaaaaaaaaaaaaaaaaa",
                        "account_sid": "ACaaaaaaaaaaaaaaaaaaaaaaaaaaaaaaaa",
                        "fax_sid": "FXaaaaaaaaaaaaaaaaaaaaaaaaaaaaaaaa",
                        "content_type": "application/pdf",
                        "date_created": "2015-07-30T20:00:00Z",
                        "date_updated": "2015-07-30T20:00:00Z",
                        "url": "https://fax.twilio.com/v1/Faxes/FXaaaaaaaaaaaaaaaaaaaaaaaaaaaaaaaa/Media/MEaaaaaaaaaaaaaaaaaaaaaaaaaaaaaaaa"
                    }],
                    "meta": {
                        "first_page_url": "https://fax.twilio.com/v1/Faxes/FXaaaaaaaaaaaaaaaaaaaaaaaaaaaaaaaa/Media?PageSize=50&Page=0",
                        "key": "media",
                        "next_page_url": null,
                        "page": 0,
                        "page_size": 50,
                        "previous_page_url": null,
                        "url": "https://fax.twilio.com/v1/Faxes/FXaaaaaaaaaaaaaaaaaaaaaaaaaaaaaaaa/Media?PageSize=50&Page=0"
                    }
                },
                "status_code": 200
            }
        }
    ],
    "delete": [
        {
            "name": "delete",
            "request": {
                "account_sid": "ACaaaaaaaaaaaaaaaaaaaaaaaaaaaaaaaa",
                "form_params": {},
                "method": "DELETE",
                "query_params": {},
                "url": "https://fax.twilio.com/v1/Faxes/FXaaaaaaaaaaaaaaaaaaaaaaaaaaaaaaaa/Media/MEaaaaaaaaaaaaaaaaaaaaaaaaaaaaaaaa"
            },
            "downstream_request": {
                "account_sid": "ACaaaaaaaaaaaaaaaaaaaaaaaaaaaaaaaa",
                "form_params": {},
                "method": "DELETE",
                "query_params": {},
                "url": "/v1/Faxes/FXaaaaaaaaaaaaaaaaaaaaaaaaaaaaaaaa/Media/MEaaaaaaaaaaaaaaaaaaaaaaaaaaaaaaaa"
            },
            "downstream_response": {
                "content": null,
                "status_code": 204
            },
            "response": {
                "content": null,
                "status_code": 204
            }
        }
    ]
}
